<?xml version="1.0" encoding="UTF-8"?>
<objects serializationModel="Studio.02.01.00">
	<object class="AudioFile" id="{d7bd78a3-33fa-4d74-8b4a-85d90714c521}">
		<property name="assetPath">
			<value>ShotgunNoAmmo.wav</value>
		</property>
		<property name="frequencyInKHz">
			<value>44.0999985</value>
		</property>
		<property name="channelCount">
			<value>2</value>
		</property>
		<property name="length">
			<value>0.090816326530612251</value>
		</property>
		<relationship name="masterAssetFolder">
			<destination>{4e60e48e-21d7-4838-b434-5081f7711d0a}</destination>
		</relationship>
	</object>
</objects>
